odoo/addons/sale_exception_stock_prebook/README.rst
odoo/addons/sale_exception_stock_prebook/__init__.py
odoo/addons/sale_exception_stock_prebook/__manifest__.py
odoo/addons/sale_exception_stock_prebook/i18n/it.po
odoo/addons/sale_exception_stock_prebook/i18n/sale_exception_stock_prebook.pot
odoo/addons/sale_exception_stock_prebook/models/__init__.py
odoo/addons/sale_exception_stock_prebook/models/sale_order.py
odoo/addons/sale_exception_stock_prebook/readme/CONTRIBUTORS.rst
odoo/addons/sale_exception_stock_prebook/readme/DESCRIPTION.rst
odoo/addons/sale_exception_stock_prebook/static/description/icon.png
odoo/addons/sale_exception_stock_prebook/static/description/index.html
odoo/addons/sale_exception_stock_prebook/tests/__init__.py
odoo/addons/sale_exception_stock_prebook/tests/test_sale_stock_prebook.py
odoo_addon_sale_exception_stock_prebook-16.0.1.1.0.1.dist-info/METADATA
odoo_addon_sale_exception_stock_prebook-16.0.1.1.0.1.dist-info/WHEEL
odoo_addon_sale_exception_stock_prebook-16.0.1.1.0.1.dist-info/top_level.txt
odoo_addon_sale_exception_stock_prebook-16.0.1.1.0.1.dist-info/RECORD
