Metadata-Version: 2.1
Name: odoo-addon-sale_exception_stock_prebook
Version: 16.0.1.1.0.1
Summary: Glue Addon to no release reservation if sale order has exceptions
Home-page: https://github.com/OCA/sale-prebook
Author: MT Software, Odoo Community Association (OCA)
Author-email: support@odoo-community.org
License: AGPL-3
Classifier: Programming Language :: Python
Classifier: Framework :: Odoo
Classifier: Framework :: Odoo :: 16.0
Classifier: License :: OSI Approved :: GNU Affero General Public License v3
Requires-Python: >=3.10
Requires-Dist: odoo-addon-sale-exception<16.1dev,>=16.0dev
Requires-Dist: odoo-addon-sale-stock-prebook<16.1dev,>=16.0dev
Requires-Dist: odoo<16.1dev,>=16.0a
